MANIFEST.in
setup.py
humilis_security/__init__.py
humilis_security/meta.yaml.j2
humilis_security/outputs.yaml.j2
humilis_security/plugin.py
humilis_security/resources.yaml.j2
humilis_security.egg-info/PKG-INFO
humilis_security.egg-info/SOURCES.txt
humilis_security.egg-info/dependency_links.txt
humilis_security.egg-info/entry_points.txt
humilis_security.egg-info/not-zip-safe
humilis_security.egg-info/requires.txt
humilis_security.egg-info/top_level.txt