Metadata-Version: 1.1
Name: humilis-security
Version: 0.0.5
Summary: Humilis plug-in to deploy security groups in a VPC
Home-page: https://github.com/humilis/humilis-security
Author: German Gomez-Herrero, FindHotel BV
Author-email: german@findhotel.net
License: MIT
Platform: UNKNOWN
Classifier: Programming Language :: Python :: 3
